LICENSE.txt
README.txt
bootstrap.py
buildout.cfg
setup.py
src/jquery/__init__.py
src/jquery.widget.egg-info/PKG-INFO
src/jquery.widget.egg-info/SOURCES.txt
src/jquery.widget.egg-info/dependency_links.txt
src/jquery.widget.egg-info/namespace_packages.txt
src/jquery.widget.egg-info/not-zip-safe
src/jquery.widget.egg-info/requires.txt
src/jquery.widget.egg-info/top_level.txt
src/jquery/widget/__init__.py
src/jquery/widget/resteditor/README.txt
src/jquery/widget/resteditor/__init__.py
src/jquery/widget/resteditor/browser.py
src/jquery/widget/resteditor/interfaces.py
src/jquery/widget/resteditor/jquery.resteditor.css
src/jquery/widget/resteditor/jquery.resteditor.js
src/jquery/widget/resteditor/tests.py
src/jquery/widget/resteditor/doc/jquery-1.1.2.js
src/jquery/widget/resteditor/doc/sample.html
src/jquery/widget/resteditor/img/restEditorBackground.gif
src/jquery/widget/resteditor/img/restEditorBold.gif
src/jquery/widget/resteditor/img/restEditorBold.png
src/jquery/widget/resteditor/img/restEditorBoldActive.gif
src/jquery/widget/resteditor/img/restEditorBoldActive.png
src/jquery/widget/resteditor/img/restEditorCode.gif
src/jquery/widget/resteditor/img/restEditorCode.png
src/jquery/widget/resteditor/img/restEditorCodeActive.gif
src/jquery/widget/resteditor/img/restEditorCodeActive.png
src/jquery/widget/resteditor/img/restEditorItalic.gif
src/jquery/widget/resteditor/img/restEditorItalic.png
src/jquery/widget/resteditor/img/restEditorItalicActive.gif
src/jquery/widget/resteditor/img/restEditorItalicActive.png
src/jquery/widget/resteditor/img/restEditorLink.gif
src/jquery/widget/resteditor/img/restEditorLink.png
src/jquery/widget/resteditor/img/restEditorLinkActive.gif
src/jquery/widget/resteditor/img/restEditorLinkActive.png
src/jquery/widget/resteditor/img/restEditorRule.gif
src/jquery/widget/resteditor/img/restEditorRule.png
src/jquery/widget/resteditor/img/restEditorRuleActive.gif
src/jquery/widget/resteditor/img/restEditorRuleActive.png
