Metadata-Version: 1.0
Name: jquery.widget
Version: 0.1.0c1
Summary: A collection of JQuery-based widgets.
Home-page: http://svn.zope.org/jquery.widget
Author: Roger Ineichen and the Zope Community
Author-email: zope3-dev@zope.org
License: ZPL 2.1
Keywords: zope3 widget jquery viewlet
Platform: UNKNOWN
Classifier: Development Status :: 4 - Beta
Classifier: Environment :: Web Environment
Classifier: Intended Audience :: Developers
Classifier: License :: OSI Approved :: Zope Public License
Classifier: Programming Language :: Python
Classifier: Natural Language :: English
Classifier: Operating System :: OS Independent
Classifier: Topic :: Internet :: WWW/HTTP
Classifier: Framework :: Zope3
